README.md
setup.py
UniExpect.egg-info/PKG-INFO
UniExpect.egg-info/SOURCES.txt
UniExpect.egg-info/dependency_links.txt
UniExpect.egg-info/entry_points.txt
UniExpect.egg-info/requires.txt
UniExpect.egg-info/top_level.txt
uniexpect/expect.py
uniexpect/main.py
uniexpect/utils.py