Metadata-Version: 1.1
Name: UniExpect
Version: 0.1
Summary: Run doctests in any REPL language
Home-page: https://github.com/alvinwan/UniExpect
Author: Alvin Wan
Author-email: hi@alvinwan.com
License: BSD
Download-URL: https://github.com/alvinwan/UniExpect/archive/0.1.zip
Platform: UNKNOWN
Classifier: Topic :: Utilities
Classifier: Intended Audience :: Developers
Classifier: Programming Language :: Python :: 3
Classifier: Topic :: Software Development :: Libraries
